vlutils/__init__.py
vlutils/config.py
vlutils/custom.py
vlutils/io.py
vlutils/logger.py
vlutils/runtime.py
vlutils/saver.py
vlutils/types.py
vlutils/utils.py
vlutils/base/__init__.py
vlutils/base/dataParallel.py
vlutils/base/decoratorContextManager.py
vlutils/base/freqHook.py
vlutils/base/module.py
vlutils/base/registry.py
vlutils/base/restorable.py
vlutils/datasets/__init__.py
vlutils/datasets/wrappers.py
vlutils/metrics/__init__.py
vlutils/metrics/helpers.py
vlutils/metrics/meter.py
vlutils/metrics/pairwise.py
vlutils/vision/__init__.py
vlutils/vision/colorSpace.py
vlutils/vision/utils.py
vlutils-0.1.28.dist-info/LICENSE
vlutils-0.1.28.dist-info/METADATA
vlutils-0.1.28.dist-info/WHEEL
vlutils-0.1.28.dist-info/top_level.txt
vlutils-0.1.28.dist-info/RECORD
