Metadata-Version: 2.1
Name: vlutils
Version: 0.1.28
Summary: VL-Group Utilities
Home-page: https://github.com/cfm-uestc/vlutils
Author: Xiaosu Zhu
Author-email: xiaosu.zhu@outlook.com
License: Apache-2.0 License
Keywords: Utilities,Utils
Platform: UNKNOWN
Classifier: Development Status :: 3 - Alpha
Classifier: Intended Audience :: Developers
Classifier: Topic :: Software Development :: Libraries
Classifier: License :: OSI Approved :: Apache Software License
Classifier: Programming Language :: Python :: 3.8
Classifier: Programming Language :: Python :: 3.9
Requires-Python: >=3.8
License-File: LICENSE
Requires-Dist: torch (>=1.9)
Requires-Dist: tqdm
Requires-Dist: rich
Requires-Dist: nvidia-ml-py3
